[
  {
    "html": "<h3> <dco>2.6.20&nbsp; \n9:20 pm</dco> &nbsp;<qco> Does New Zealand exist?</qco> </h3>"
  },
  {
    "html": "<h3> <dco>2.6.20&nbsp; \n8:58 pm</dco> &nbsp;<qco> Do you ever get a chance to look at the house and I will be there at least I can do it for you if you want to see me and I will be there at least I can do it tomorrow if you want to see the movie is at least I can do it for you.</qco> </h3>"
  },
  {
    "html": "<h3> <dco>2.6.20&nbsp; \n8:40 pm</dco> &nbsp;<qco> Why do you never update your notebook anymore?</qco> </h3>"
  },
  {
    "html": "<h3> <dco>2.6.20&nbsp; \n8:31 pm</dco> &nbsp;<qco> whats the latest thing you've learned from a song?</qco></h3><h3><qco> &nbsp;&nbsp;&nbsp;&nbsp;&nbsp; and which song?</qco> </h3>"
  },
  {
    "html": "<h3> <dco>2.6.20&nbsp; \n8:07 pm</dco> &nbsp;<qco> if i feed soap to my pet rock what will happen</qco> </h3>"
  },
  {
    "html": "<h3> <dco>2.6.20&nbsp; \n8:02 pm</dco> &nbsp;<qco> What are your core philosophical constructs that you use daily?</qco> </h3>"
  },
  {
    "html": "<h3> <dco>2.6.20&nbsp; \n8:00 pm</dco> &nbsp;<qco> What is something that makes you feel truly fulfilled;</qco></h3><h3><qco> &nbsp;&nbsp;&nbsp;&nbsp;&nbsp;&nbsp;are there subjects (i.e. science, math, etc.) That truly fulfill you?</qco> </h3>"
  },
  {
    "html": "<h3> <dco>2.6.20&nbsp; \n7:35 pm</dco> &nbsp;<qco> Whats your take on this year's US Democratic primary elections?&nbsp;</qco> </h3><i>\"The ride of a lifetime.\" \"Unforgettable\". \"Lester Holt's head is even taller than i remembered it\"</i>"
  },
  {
    "html": "<h3> <dco>2.6.20&nbsp; \n7:14 pm</dco> &nbsp;<qco> How does one overcome the moral questionability of rhinoceros</qco> </h3>"
  },
  {
    "html": "<h3> <dco>2.6.20&nbsp; \n6:18 pm</dco> &nbsp;<qco> Did you ever climb the Water Tower</qco> </h3>"
  },
  {
    "html": "<h3> <dco>2.6.20&nbsp; \n4:56 pm</dco> &nbsp;<qco> Especially because all my improvisation at the piano seems to fall into D flat, it feels like I fall into the same basic patterns every time I play. Do you have a key you \"naturally\" improvise in?</qco></h3><h3><qco> &nbsp;&nbsp;&nbsp;&nbsp;&nbsp; If this feels like a problem, what's the solution?</qco> </h3>"
  },
  {
    "html": "<h3> <dco>2.6.20&nbsp; \n4:29 pm</dco> &nbsp;<qco> How do you feel about capital letters?</qco> </h3>"
  },
  {
    "html": "<h3> <dco>2.6.20&nbsp; \n4:01 pm</dco> &nbsp;<qco> what the heck is a song???</qco> </h3>"
  },
  {
    "html": "<h3> <dco>2.6.20&nbsp; \n3:48 pm</dco> &nbsp;<qco> What should you do when you do a bad thing but then you get apologized but you redo the same thing again? (idk if I explained this one right)&nbsp;</qco> </h3>"
  },
  {
    "html": "<h3> <dco>2.6.20&nbsp; \n3:39 pm</dco> &nbsp;<qco> what do i do if i don't remember <remq></remq>what question i wrote to you?</qco> </h3><a href=\"q.php?date=202001221636\" target=\"_blank\">clicking here</a>"
  },
  {
    "html": "<h3> <dco>2.6.20&nbsp; \n3:37 pm</dco> &nbsp;<qco> have you consider recording vocals in a professional studio?</qco> </h3>"
  },
  {
    "html": "<h3> <dco>2.6.20&nbsp; \n2:52 pm</dco> &nbsp;<qco> how does one make a pizza?</qco> </h3>"
  },
  {
    "html": "<h3> <dco>2.6.20&nbsp; \n2:44 pm</dco> &nbsp;<qco> what key is easiest for you to play in on the keyboard</qco> </h3>"
  },
  {
    "html": "<h3> <dco>2.6.20&nbsp; \n2:33 pm</dco> &nbsp;<qco> why did cortez come and smash it</qco> </h3>"
  },
  {
    "html": "<h3> <dco>2.6.20&nbsp; \n1:54 pm</dco> &nbsp;<qco> Will you ever write a new note on notebook section?</qco> </h3>"
  },
  {
    "html": "<h3> <dco>2.6.20&nbsp; \n1:41 pm</dco> &nbsp;<qco> has there ever been a good american president</qco> </h3>"
  },
  {
    "html": "<h3> <dco>2.6.20&nbsp; \n12:55 pm</dco> &nbsp;<qco> Do you think there are so many words to describe the same thing because lyricists and poets have just been making up words to complete rhymes and deciding they mean what they need them to mean?&nbsp;</qco> </h3>"
  },
  {
    "html": "<h3> <dco>2.6.20&nbsp; \n12:39 pm</dco> &nbsp;<qco> as a fraction and/or percentage, how much of your music catalog have you actually produced?</qco> </h3>"
  },
  {
    "html": "<h3> <dco>2.6.20&nbsp; \n12:18 pm</dco> &nbsp;<qco> what drawing program on mac do you use</qco> </h3>"
  },
  {
    "html": "<h3> <dco>2.6.20&nbsp; \n12:06 pm</dco> &nbsp;<qco> Hello, How big is the universe?</qco> </h3>"
  },
  {
    "html": "<h3> <dco>2.6.20&nbsp; \n11:38 am</dco> &nbsp;<qco> thoughts about trees?</qco> </h3>"
  },
  {
    "html": "<h3> <dco>2.6.20&nbsp; \n11:34 am</dco> &nbsp;<qco> What is your favorite font?</qco> </h3>"
  },
  {
    "html": "<h3> <dco>2.6.20&nbsp; \n11:01 am</dco> &nbsp;<qco> how did you get into singing?</qco> </h3>"
  },
  {
    "html": "<h3> <dco>2.6.20&nbsp; \n10:03 am</dco> &nbsp;<qco> Can a match box?</qco> </h3>"
  },
  {
    "html": "<h3> <dco>2.6.20&nbsp; \n9:49 am</dco> &nbsp;<qco> Is 'Bob' short for 'Robert' or 'Bobert' ?</qco> </h3>"
  },
  {
    "html": "<h3> <dco>2.6.20&nbsp; \n8:25 am</dco> &nbsp;<qco> have you ever been betrayed, abandoned, or otherwise made an incoherent fool out of?</qco> </h3>"
  },
  {
    "html": "<h3> <dco>2.6.20&nbsp; \n7:44 am</dco> &nbsp;<qco> Any advice on how to write music a bit more differently but in a good way? Especially when I listened to too much of mainstream stuff and being subconsciously influenced by them. Currently trying to compose more 'flexible' music but my ideas are always based on mainstream music (eg. melodies are always in a 8-bar structure etc.) and whenever I try to experiment around to get something different from conventional writing most of the time it would just sound cringy</qco> </h3>"
  },
  {
    "html": "<h3> <dco>2.6.20&nbsp; \n7:42 am</dco> &nbsp;<qco> where should I start with learning how to play a keyboard?</qco> </h3>"
  },
  {
    "html": "<h3> <dco>2.6.20&nbsp; \n7:13 am</dco> &nbsp;<qco> How do I motivate?</qco> </h3>"
  },
  {
    "html": "<h3> <dco>2.6.20&nbsp; \n7:01 am</dco> &nbsp;<qco> if you toast a bagel is it still a bagel&nbsp;</qco> </h3>"
  },
  {
    "html": "<h3> <dco>2.6.20&nbsp; \n6:16 am</dco> &nbsp;<qco> what's the best hold music you've ever heard on a phone call?</qco> </h3>"
  },
  {
    "html": "<h3> <dco>2.6.20&nbsp; \n5:41 am</dco> &nbsp;<qco> What if the world is made out of cheese?</qco> </h3>"
  },
  {
    "html": "<h3> <dco>2.6.20&nbsp; \n5:31 am</dco> &nbsp;<qco> Is the catchiness of your songs because of the melody or the rhythm section?&nbsp;</qco> </h3>"
  },
  {
    "html": "<h3> <dco>2.6.20&nbsp; \n4:04 am</dco> &nbsp;<qco> Do you know how that thing inventor is coming along?</qco> </h3>"
  },
  {
    "html": "<h3> <dco>2.6.20&nbsp; \n3:51 am</dco> &nbsp;<qco> Should Kevin Costner open a chain of convenience stores called \"Kevin Eleven\"? </qco></h3><h3><qco> &nbsp;&nbsp;&nbsp;&nbsp;&nbsp;What would you buy there?</qco> </h3>"
  },
  {
    "html": "<h3> <dco>2.6.20&nbsp; \n3:42 am</dco> &nbsp;<qco> How do you feel about the fact that most stars have already been born, and the number of lights in the sky will only go down until nothing but a homogenous, black, cold void of photons with nothing to hit remains, and nothing can ever happen again, dooming the cosmos itself to die just like everyone it spawned?</qco> </h3>"
  },
  {
    "html": "<h3> <dco>2.6.20&nbsp; \n3:30 am</dco> &nbsp;<qco> why is philosophy so hard</qco> </h3>"
  },
  {
    "html": "<h3> <dco>2.6.20&nbsp; \n2:54 am</dco> &nbsp;<qco> <a href=\"q.php?date=202002032016\">2.3.20&nbsp;&nbsp;8:16 pm</a>  you didn't really type that with boxing gloves did u</qco> </h3><a href=\"q.php?date=201707271950\" target=\"_blank\">previous time</a>"
  },
  {
    "html": "<h3> <dco>2.6.20&nbsp; \n2:20 am</dco> &nbsp;<qco> what are your opinions on the much anticipated end of the universe?</qco> </h3>"
  },
  {
    "html": "<h3> <dco>2.6.20&nbsp; \n2:20 am</dco> &nbsp;<qco> i took your advise and wrote a folktale but i'm worried its a bit too heavy handed on the allegory. what should i do?</qco> </h3>"
  },
  {
    "html": "<h3> <dco>2.6.20&nbsp; \n1:23 am</dco> &nbsp;<qco> How lazy have you been during the past 10 months?</qco> </h3>"
  },
  {
    "html": "<h3> <dco>2.6.20&nbsp; \n12:47 am</dco> &nbsp;<qco> I find myself in a conundrum often, where someone says something, and I can perceive (perhaps incorrectly) the type of reaction they want to get from saying said things. </qco></h3><h3><qco> &nbsp;&nbsp;&nbsp;&nbsp;&nbsp;And it kinda shortcircuits my brain. where I happen to believe I know what they want to hear, yet I don't naturally tend towards that reaction. Which leaves me feeling like i let them down. Do you have any tips for dealing with those moments? </qco></h3><h3><qco> &nbsp;&nbsp;&nbsp;&nbsp;&nbsp;Where you just want to react as you would, regardless of what you may assume is the desired response to their call. It's like I feel that i let them down whenever i dont give the response i believe they are looking for.&nbsp;</qco> </h3>"
  },
  {
    "html": "<h3> <dco>2.6.20&nbsp; \n12:46 am</dco> &nbsp;<qco> if you could do anything in the entire world, what would you do?</qco> </h3>"
  },
  {
    "html": "<h3> <dco>2.6.20&nbsp; \n12:31 am</dco> &nbsp;<qco> When is your next video</qco> </h3>"
  },
  {
    "html": "<h3> <dco>2.6.20&nbsp; \n12:10 am</dco> &nbsp;<qco> what does it feel like to chew 5 gum</qco> </h3>"
  }
]
