[
  {
    "html": "<h3> <dco>7.7.20&nbsp; \n10:15 pm</dco> &nbsp;<qco> Do you feel alright with the days gone by?</qco> </h3>      \noh now you've got me thinking\n<br><br>"
  },
  {
    "html": "<h3> <dco>7.7.20&nbsp; \n10:01 pm</dco> &nbsp;<qco> movin into my first apartment, any tips?</qco> </h3>      \nfirst thing to do is to learn the address of the apartment\n<br><br>"
  },
  {
    "html": "<h3> <dco>7.7.20&nbsp; \n9:51 pm</dco> &nbsp;<qco> Im playing piano but my hands are too small for some of the chords what do I do mr bill</qco> </h3>      \nyou could check out some michel petrucciani for some inspiration\n<br><br>"
  },
  {
    "html": "<h3> <dco>7.7.20&nbsp; \n9:50 pm</dco> &nbsp;<qco> what's your opinion on sleep</qco> </h3>      \ndifficult to even imagine\n<br><br>"
  },
  {
    "html": "<h3> <dco>7.7.20&nbsp; \n9:50 pm</dco> &nbsp;<qco> Do you know how cool you are?</qco> </h3>      \ni am working with my therapist to try to raise this amount\n<br><br>"
  },
  {
    "html": "<h3> <dco>7.7.20&nbsp; \n9:50 pm</dco> &nbsp;<qco> Is anyone other than me, truly conscious?&nbsp;</qco> </h3>      \nyes\n<br><br>"
  },
  {
    "html": "<h3> <dco>7.7.20&nbsp; \n9:49 pm</dco> &nbsp;<qco> Do you do lyrics or music first</qco> </h3>      \nsametime\n<br><br>"
  },
  {
    "html": "<h3> <dco>7.7.20&nbsp; \n9:46 pm</dco> &nbsp;<qco> Thoughts on the United Kingdom?</qco> </h3>      \nsometimes i wonder if it could Unite even more\n<br><br>"
  },
  {
    "html": "<h3> <dco>7.7.20&nbsp; \n9:43 pm</dco> &nbsp;<qco> What is your opinion on cable television?</qco> </h3>      \nthe whole trick to it is figuring out which end of the cable to put the television\n<br><br>"
  },
  {
    "html": "<h3> <dco>7.7.20&nbsp; \n9:43 pm</dco> &nbsp;<qco> Hi Bill, your videos help me through tough times, was wondering how you are doing</qco></h3>      pretty good<h3><qco> &nbsp;&nbsp;&nbsp;&nbsp;&nbsp; and what's ur next project?</qco></h3>      not sure, but my current project is video making<h3><qco> &nbsp;&nbsp;&nbsp;&nbsp;&nbsp; Thanks for keeping me from ending it all and making me feel like anything is possible in this world!</qco> </h3>      \nthank you for your sudden outburst of friendlyness\n<br><br>"
  },
  {
    "html": "<h3> <dco>7.7.20&nbsp; \n9:25 pm</dco> &nbsp;<qco> Do you write lyrics before melody, or with?</qco> </h3>      \nextremely with\n\n<br><br>"
  },
  {
    "html": "<h3> <dco>7.7.20&nbsp; \n9:10 pm</dco> &nbsp;<qco> Why does your music make me so over joyed that I can't even operate correctly?</qco> </h3>      \ncould have been that little bit of goat's milk i slipped in there\n<br><br>"
  },
  {
    "html": "<h3> <dco>7.7.20&nbsp; \n8:39 pm</dco> &nbsp;<qco> what is life? </qco></h3>      small rocks,<h3><qco> &nbsp;&nbsp;&nbsp;&nbsp;&nbsp;do we really know the answer?</qco></h3>      you can make your own answers<h3><qco> &nbsp;&nbsp;&nbsp;&nbsp;&nbsp; i have so many ueqstions.</qco> </h3>      \n\n<br><br>"
  },
  {
    "html": "<h3> <dco>7.7.20&nbsp; \n8:22 pm</dco> &nbsp;<qco> What is math?</qco> </h3>      \neverything\n<br><br>"
  },
  {
    "html": "<h3> <dco>7.7.20&nbsp; \n8:18 pm</dco> &nbsp;<qco> Favorite flavor of pizza</qco> </h3>      \nslice of\n<br><br>"
  },
  {
    "html": "<h3> <dco>7.7.20&nbsp; \n7:59 pm</dco> &nbsp;<qco> Are you a human being?</qco> </h3>      \noh that would explain a lot\n<br><br>"
  },
  {
    "html": "<h3> <dco>7.7.20&nbsp; \n7:52 pm</dco> &nbsp;<qco> what's your favorite brass instrument</qco> </h3>      \ntrumpet\n<br><br>"
  },
  {
    "html": "<h3> <dco>7.7.20&nbsp; \n7:42 pm</dco> &nbsp;<qco> How do I ask a good question?</qco> </h3>      \nimpossible. it can't be done\n<br><br>"
  },
  {
    "html": "<h3> <dco>7.7.20&nbsp; \n7:42 pm</dco> &nbsp;<qco> will you ever release instrumentals for your songs? </qco></h3>      yes<h3><qco> &nbsp;&nbsp;&nbsp;&nbsp;&nbsp;i would like to hear all the neat details that are covered up by your voice</qco> </h3>      \n\n<br><br>"
  },
  {
    "html": "<h3> <dco>7.7.20&nbsp; \n7:37 pm</dco> &nbsp;<qco> Do you postpone your next video every time someone asks you about it?</qco> </h3>      \nno\n<br><br>"
  },
  {
    "html": "<h3> <dco>7.7.20&nbsp; \n7:36 pm</dco> &nbsp;<qco> how do you make your videos?</qco> </h3>      \ni'm figuring that out right now\n\n<br><br>"
  },
  {
    "html": "<h3> <dco>7.7.20&nbsp; \n7:27 pm</dco> &nbsp;<qco> can you pick a number between 1-100 for me?</qco> </h3>      \n<a href=\"sol4xcajg0rc9qc.php\" target=\"_blank\">sure</a>\n<br><br>"
  },
  {
    "html": "<h3> <dco>7.7.20&nbsp; \n7:25 pm</dco> &nbsp;<qco> How do you get bad thoughts out of your head?\n<br></qco> </h3>      \nlooks like it's time to start your autobiography\n<br><br>"
  },
  {
    "html": "<h3> <dco>7.7.20&nbsp; \n7:21 pm</dco> &nbsp;<qco> What is corn?</qco> </h3>      \nit's like a lego set that you can only take apart\n<br><br>"
  },
  {
    "html": "<h3> <dco>7.7.20&nbsp; \n7:20 pm</dco> &nbsp;<qco> why do you answer questions</qco> </h3>      \ncould be some sort of conspiracy\n\n<br><br>"
  },
  {
    "html": "<h3> <dco>7.7.20&nbsp; \n7:01 pm</dco> &nbsp;<qco> pancakes or waffles?</qco> </h3>      \nah, the classic cry of the person who has yet to discover waff cakes\n<br><br>"
  },
  {
    "html": "<h3> <dco>7.7.20&nbsp; \n6:57 pm</dco> &nbsp;<qco> What is your upcoming content going to look like?</qco> </h3>      \ndreams\n<br><br>"
  },
  {
    "html": "<h3> <dco>7.7.20&nbsp; \n6:33 pm</dco> &nbsp;<qco> whats your favorite kind of food?</qco> </h3>      \nsludge\n<br><br>"
  },
  {
    "html": "<h3> <dco>7.7.20&nbsp; \n6:27 pm</dco> &nbsp;<qco> How long will it be before time passes?</qco> </h3>      \noh, a few half dozen years maybe\n<br><br>"
  },
  {
    "html": "<h3> <dco>7.7.20&nbsp; \n6:25 pm</dco> &nbsp;<qco> how to get older but stay a kid at the same time</qco> </h3>      \n(whispers) 'memes'\n<br><br>"
  },
  {
    "html": "<h3> <dco>7.7.20&nbsp; \n5:40 pm</dco> &nbsp;<qco> Can you say something in garfield language?&nbsp;</qco> </h3>      \nAARGH\n<br><br>"
  },
  {
    "html": "<h3> <dco>7.7.20&nbsp; \n5:28 pm</dco> &nbsp;<qco> Best way to cheat at chess</qco> </h3>      \npoison your opponent\n<br><br>"
  },
  {
    "html": "<h3> <dco>7.7.20&nbsp; \n5:20 pm</dco> &nbsp;<qco> do you have any computer tips</qco> </h3>      \nyes, try to get on its good side\n<br><br>"
  },
  {
    "html": "<h3> <dco>7.7.20&nbsp; \n5:19 pm</dco> &nbsp;<qco> Do you think trees are cool?</qco> </h3>      \nyes\n<br><br>"
  },
  {
    "html": "<h3> <dco>7.7.20&nbsp; \n5:09 pm</dco> &nbsp;<qco> whats the most lame thing one can do&nbsp;</qco> </h3>      \ndestroy the whole universe\n<br><br>"
  },
  {
    "html": "<h3> <dco>7.7.20&nbsp; \n5:01 pm</dco> &nbsp;<qco> What is the definition of normal to you?</qco> </h3>      \na sort of light and breezy feeling\n<br><br>"
  },
  {
    "html": "<h3> <dco>7.7.20&nbsp; \n4:58 pm</dco> &nbsp;<qco> how to open a coffin?</qco> </h3>      \nit's way easier to open it from the inside\n<br><br>"
  },
  {
    "html": "<h3> <dco>7.7.20&nbsp; \n4:32 pm</dco> &nbsp;<qco> thoughts on hot pockets?</qco> </h3>      \ntoo hot\n<br><br>"
  },
  {
    "html": "<h3> <dco>7.7.20&nbsp; \n4:26 pm</dco> &nbsp;<qco> Is it good to start writing and singing songs? Im starting to do these things.&nbsp;</qco> </h3>      \ndepending on your personality type, it might save your life\n<br><br>"
  },
  {
    "html": "<h3> <dco>7.7.20&nbsp; \n3:57 pm</dco> &nbsp;<qco> How do you open words\n<br></qco> </h3>      \nfind out their etymology\n<br><br>"
  },
  {
    "html": "<h3> <dco>7.7.20&nbsp; \n3:55 pm</dco> &nbsp;<qco> is spam spiced ham or is ham bland spam?</qco> </h3>      \nboth. they are both on the ham spam spectrum\n<br><br>"
  },
  {
    "html": "<h3> <dco>7.7.20&nbsp; \n3:41 pm</dco> &nbsp;<qco> Where did your clownfish come from?&nbsp;</qco> </h3>      \nit's been in the family for years\n<br><br>"
  },
  {
    "html": "<h3> <dco>7.7.20&nbsp; \n3:22 pm</dco> &nbsp;<qco> Who's your favorite music person?</qco> </h3>      \ncould be you\n<br><br>"
  },
  {
    "html": "<h3> <dco>7.7.20&nbsp; \n3:18 pm</dco> &nbsp;<qco> how are carrot sticks made?</qco> </h3>      \nthey are tenderly forged in the heavens\n<br><br>"
  },
  {
    "html": "<h3> <dco>7.7.20&nbsp; \n3:17 pm</dco> &nbsp;<qco> What's your opinion on the number \"32\"?</qco> </h3>      \nvery even. even more even than most numbers\n<br><br>"
  },
  {
    "html": "<h3> <dco>7.7.20&nbsp; \n3:12 pm</dco> &nbsp;<qco> Are all the questions here made by you and you just pretend that they are from other people?&nbsp;</qco> </h3>      \nno\n<br><br>"
  },
  {
    "html": "<h3> <dco>7.7.20&nbsp; \n3:09 pm</dco> &nbsp;<qco> is there anything you hate?</qco> </h3>      \nsalmon\n<br><br>"
  },
  {
    "html": "<h3> <dco>7.7.20&nbsp; \n2:56 pm</dco> &nbsp;<qco> Why do salmon appear so much in your videos?&nbsp;</qco> </h3>      \ni only recall using it in 1 video\n<br><br>"
  },
  {
    "html": "<h3> <dco>7.7.20&nbsp; \n2:15 pm</dco> &nbsp;<qco> Is Wyoming real?</qco> </h3>      \nyes, but i can't prove it right now\n<br><br>"
  },
  {
    "html": "<h3> <dco>7.7.20&nbsp; \n2:08 pm</dco> &nbsp;<qco> why is garlic bread so good with pasta</qco> </h3>      \nbecause pasta is so bad\n<br><br>"
  }
]
