[
  {
    "html": "<h3> <font color=\"#E9EC54\">9.8.16&nbsp;\n4:09 pm</font> &nbsp;<font color=\"#B387FF\"> how will the two koreas reunite as one nation</font> </h3>"
  },
  {
    "html": "<h3> <font color=\"#E9EC54\">9.8.16&nbsp;\n4:01 pm</font> &nbsp;<font color=\"#B387FF\"> how to deal with feeling bad when you know you have disappointed someone else</font> </h3>"
  },
  {
    "html": "<h3> <font color=\"#E9EC54\">9.8.16&nbsp;\n3:24 pm</font> &nbsp;<font color=\"#B387FF\"> how do I deal with emotional devastation at the hands of the person I care most about and also how are you today</font> </h3>"
  },
  {
    "html": "<h3> <font color=\"#E9EC54\">9.8.16&nbsp;\n2:51 pm</font> &nbsp;<font color=\"#B387FF\"> what's your opinion on horses?</font> </h3>"
  },
  {
    "html": "<h3> <font color=\"#E9EC54\">9.8.16&nbsp;\n1:29 pm</font> &nbsp;<font color=\"#B387FF\"> is it possible to anagram \"abcdefghijklmnopqrstuvwxyz\"?</font> </h3>"
  },
  {
    "html": "<h3> <font color=\"#E9EC54\">9.8.16&nbsp;\n11:30 am</font> &nbsp;<font color=\"#B387FF\"> is the truth the real thing or what everyone in the entire world believes?</font> </h3>"
  },
  {
    "html": "<h3> <font color=\"#E9EC54\">9.8.16&nbsp;\n11:10 am</font> &nbsp;<font color=\"#B387FF\"> Have you ever had a day in which you didn't wanna do music at all but you know that you have to? Like you're completely blocked because you simpley aren't in the mood. How do you overcome that?</font> </h3>"
  },
  {
    "html": "<h3> <font color=\"#E9EC54\">9.8.16&nbsp;\n10:31 am</font> &nbsp;<font color=\"#B387FF\"> Are you a perfectionist?</font> </h3>"
  },
  {
    "html": "<h3> <font color=\"#E9EC54\">9.8.16&nbsp;\n8:40 am</font> &nbsp;<font color=\"#B387FF\"> is gravity a permanent thing?</font> </h3>"
  },
  {
    "html": "<h3> <font color=\"#E9EC54\">9.8.16&nbsp;\n2:32 am</font> &nbsp;<font color=\"#B387FF\"> do you have a \"best of\" page where you can list a small number of your most memorable question/answer pairs?</font> </h3>"
  },
  {
    "html": "<h3> <font color=\"#E9EC54\">9.8.16&nbsp;\n12:37 am</font> &nbsp;<font color=\"#B387FF\"> How do I get crazy?</font> </h3>"
  },
  {
    "html": "<h3> <font color=\"#E9EC54\">9.8.16&nbsp;\n12:30 am</font> &nbsp;<font color=\"#B387FF\"> how do i get high without using drugs</font> </h3>"
  },
  {
    "html": "<h3> <font color=\"#E9EC54\">9.7.16&nbsp;\n11:46 pm</font> &nbsp;<font color=\"#B387FF\"> How do we unify general relativity and quantum mechanics?</font> </h3>"
  },
  {
    "html": "<h3> <font color=\"#E9EC54\">9.7.16&nbsp;\n8:58 pm</font> &nbsp;<font color=\"#B387FF\"> Are you going to make more videos?</font> </h3>"
  },
  {
    "html": "<h3> <font color=\"#E9EC54\">9.7.16&nbsp;\n8:21 pm</font> &nbsp;<font color=\"#B387FF\"> What inspired your visual style?</font> </h3>"
  },
  {
    "html": "<h3> <font color=\"#E9EC54\">9.7.16&nbsp;\n6:42 pm</font> &nbsp;<font color=\"#B387FF\"> do you like to calculate taxes </font> </h3>"
  },
  {
    "html": "<h3> <font color=\"#E9EC54\">9.7.16&nbsp;\n5:38 pm</font> &nbsp;<font color=\"#B387FF\"> do you think good journalism will continue, even though nobody will pay for it?</font> </h3>"
  },
  {
    "html": "<h3> <font color=\"#E9EC54\">9.7.16&nbsp;\n4:48 pm</font> &nbsp;<font color=\"#B387FF\"> are electrons affected by gravity</font> </h3>"
  },
  {
    "html": "<h3> <font color=\"#E9EC54\">9.7.16&nbsp;\n4:45 pm</font> &nbsp;<font color=\"#B387FF\"> I've watched all the videos in the reality section of the website and I think they're amazing. Will there be more?</font> </h3>"
  },
  {
    "html": "<h3> <font color=\"#E9EC54\">9.7.16&nbsp;\n4:30 pm</font> &nbsp;<font color=\"#B387FF\"> the Oxford comma is a comma used after the penultimate item in a list of three or more items, before ÔandÕ or ÔorÕ (e.g., an Italian painter, sculptor, and architect ).\ndo you feel enlightened now? has this knowledge assisted you in your day-to-day life?\n\n\n\n</font> </h3>"
  },
  {
    "html": "<h3> <font color=\"#E9EC54\">9.7.16&nbsp;\n3:40 pm</font> &nbsp;<font color=\"#B387FF\"> What is your percentage of honesty while answering these questions?</font> </h3>"
  },
  {
    "html": "<h3> <font color=\"#E9EC54\">9.7.16&nbsp;\n3:32 pm</font> &nbsp;<font color=\"#B387FF\"> do you think that you are crazy or creative? or maybe both\n\n\n</font> </h3>"
  },
  {
    "html": "<h3> <font color=\"#E9EC54\">9.7.16&nbsp;\n3:02 pm</font> &nbsp;<font color=\"#B387FF\"> are there any animals that are either better or worse than foxes? if not, is such an animal even theoretically possible?</font> </h3>"
  },
  {
    "html": "<h3> <font color=\"#E9EC54\">9.7.16&nbsp;\n1:56 pm</font> &nbsp;<font color=\"#B387FF\"> Soft or hard shell tacos?</font> </h3>"
  },
  {
    "html": "<h3> <font color=\"#E9EC54\">9.7.16&nbsp;\n1:12 pm</font> &nbsp;<font color=\"#B387FF\"> my five year old did not understand an explanation on r/explainlikeimfive. is he mentally retarded?</font> </h3>"
  },
  {
    "html": "<h3> <font color=\"#E9EC54\">9.7.16&nbsp;\n12:56 pm</font> &nbsp;<font color=\"#B387FF\"> What is the most important thing in your life?</font> </h3>"
  },
  {
    "html": "<h3> <font color=\"#E9EC54\">9.7.16&nbsp;\n12:13 pm</font> &nbsp;<font color=\"#B387FF\"> What is your opinion on the color beige?</font> </h3>"
  },
  {
    "html": "<h3> <font color=\"#E9EC54\">9.7.16&nbsp;\n5:42 am</font> &nbsp;<font color=\"#B387FF\"> Are you available to do <a href=\"commissions1.html\">commissions</a>?</font> </h3>"
  },
  {
    "html": "<h3> <font color=\"#E9EC54\">9.7.16&nbsp;\n2:13 am</font> &nbsp;<font color=\"#B387FF\"> do you like to draw</font> </h3>"
  },
  {
    "html": "<h3> <font color=\"#E9EC54\">9.7.16&nbsp;\n2:03 am</font> &nbsp;<font color=\"#B387FF\"> What is your drink of choice?</font> </h3>"
  },
  {
    "html": "<h3> <font color=\"#E9EC54\">9.7.16&nbsp;\n1:46 am</font> &nbsp;<font color=\"#B387FF\"> How do you not let perfectionism keep you from finishing something</font> </h3>"
  },
  {
    "html": "<h3> <font color=\"#E9EC54\">9.7.16&nbsp;\n1:07 am</font> &nbsp;<font color=\"#B387FF\"> what's your <a href=\"opinion-on-opinions.html\">opinion on opinions</a> people give you so you can opinionate on those opinions?</font> </h3>"
  },
  {
    "html": "<h3> <font color=\"#E9EC54\">9.6.16&nbsp;\n11:30 pm</font> &nbsp;<font color=\"#B387FF\"> whats your least favorite kind of question to answer</font> </h3>"
  },
  {
    "html": "<h3> <font color=\"#E9EC54\">9.6.16&nbsp;\n11:06 pm</font> &nbsp;<font color=\"#B387FF\"> I really enjoyed your video on the History of Japan. <a href=\"country-requests.html\">Will you consider doing more videos on other countries?</a> </font> </h3>"
  },
  {
    "html": "<h3> <font color=\"#E9EC54\">9.6.16&nbsp;\n10:36 pm</font> &nbsp;<font color=\"#B387FF\"> Pepsi or Cocaine</font> </h3>"
  },
  {
    "html": "<h3> <font color=\"#E9EC54\">9.6.16&nbsp;\n10:10 pm</font> &nbsp;<font color=\"#B387FF\"> Are different cultures good?</font> </h3>"
  },
  {
    "html": "<h3> <font color=\"#E9EC54\">9.6.16&nbsp;\n10:00 pm</font> &nbsp;<font color=\"#B387FF\"> do questions ever annoy you? any examples?</font> </h3>"
  },
  {
    "html": "<h3> <font color=\"#E9EC54\">9.6.16&nbsp;\n10:00 pm</font> &nbsp;<font color=\"#B387FF\"> How do I beat social anxiety?</font> </h3>"
  },
  {
    "html": "<h3> <font color=\"#E9EC54\">9.6.16&nbsp;\n9:25 pm</font> &nbsp;<font color=\"#B387FF\"> Are you annoyed by people uploading your content to Facebook and potentially making money off of it?</font> </h3>"
  },
  {
    "html": "<h3> <font color=\"#E9EC54\">9.6.16&nbsp;\n9:22 pm</font> &nbsp;<font color=\"#B387FF\"> Any thoughts towards sports? I feel like some people go overboard in how highly they treat it, but dunno your take.</font> </h3><a href=\"https://www.twitter.com/billwurtz/status/762424844625453056\">www.twitter.com/billwurtz/status/762424844625453056</a>"
  },
  {
    "html": "<h3> <font color=\"#E9EC54\">9.6.16&nbsp;\n8:32 pm</font> &nbsp;<font color=\"#B387FF\"> is there any way to not feel blue while in school?</font> </h3>"
  },
  {
    "html": "<h3> <font color=\"#E9EC54\">9.6.16&nbsp;\n7:52 pm</font> &nbsp;<font color=\"#B387FF\"> What is your purpose? </font> </h3>"
  },
  {
    "html": "<h3> <font color=\"#E9EC54\">9.6.16&nbsp;\n7:36 pm</font> &nbsp;<font color=\"#B387FF\"> do you ever forget how your own songs go if you don't hear or play it in a while?</font> </h3>"
  },
  {
    "html": "<h3> <font color=\"#E9EC54\">9.6.16&nbsp;\n7:26 pm</font> &nbsp;<font color=\"#B387FF\"> Is the note on \"it's\" in \"it's ok to have feelings\" an A, a G, or a D?</font> </h3>"
  },
  {
    "html": "<h3> <font color=\"#E9EC54\">9.6.16&nbsp;\n6:09 pm</font> &nbsp;<font color=\"#B387FF\"> do you agree that life is too short &amp; special to waste time getting annoyed at things you can't change? </font> </h3>"
  },
  {
    "html": "<h3> <font color=\"#E9EC54\">9.6.16&nbsp;\n4:31 pm</font> &nbsp;<font color=\"#B387FF\"> What does \"ad lib\" in music mean</font> </h3>"
  },
  {
    "html": "<h3> <font color=\"#E9EC54\">9.6.16&nbsp;\n12:18 pm</font> &nbsp;<font color=\"#B387FF\"> have you ever capitalized a letter</font> </h3>"
  },
  {
    "html": "<h3> <font color=\"#E9EC54\">9.6.16&nbsp;\n11:38 am</font> &nbsp;<font color=\"#B387FF\"> do you prefer pencils or pens?</font> </h3>"
  },
  {
    "html": "<h3> <font color=\"#E9EC54\">9.6.16&nbsp;\n11:28 am</font> &nbsp;<font color=\"#B387FF\"> 日本語を話せますか。</font> </h3>"
  },
  {
    "html": "<h3> <font color=\"#E9EC54\">9.6.16&nbsp;\n10:16 am</font> &nbsp;<font color=\"#B387FF\"> what do i do if i don't have a plan b?</font> </h3>"
  }
]
