[
  {
    "html": "<h3> <dco>1.12.20&nbsp; \n12:21 am</dco> &nbsp;<qco> is a typo made consciously still a typo?</qco> </h3><br><br>"
  },
  {
    "html": "<h3> <dco>1.11.20&nbsp; \n11:56 pm</dco> &nbsp;<qco> Just dropping by to ask what number the countdown is @</qco> </h3><br><br>"
  },
  {
    "html": "<h3> <dco>1.11.20&nbsp; \n11:48 pm</dco> &nbsp;<qco> follow up: what was the inspiration behind \"at the airport terminal\"</qco> </h3><br><br>"
  },
  {
    "html": "<h3> <dco>1.11.20&nbsp; \n11:18 pm</dco> &nbsp;<qco> In your long description of the \"might quit\" schedule last year you talked about how uselessitis happens when \"experimenting\". The quotes around \"experimenting\" makes it seem like to don't like the idea?</qco> </h3><br><br>"
  },
  {
    "html": "<h3> <dco>1.11.20&nbsp; \n11:04 pm</dco> &nbsp;<qco> instant regret is wacky i love it. how about you bill how do you feel about INSANT REGRET!~!!!</qco> </h3><br><br>"
  },
  {
    "html": "<h3> <dco>1.11.20&nbsp; \n10:10 pm</dco> &nbsp;<qco> do you know updog</qco> </h3><br><br>"
  },
  {
    "html": "<h3> <dco>1.11.20&nbsp; \n10:05 pm</dco> &nbsp;<qco> What are illusions?</qco> </h3><br><br>"
  },
  {
    "html": "<h3> <dco>1.11.20&nbsp; \n9:40 pm</dco> &nbsp;<qco> what temperature do you enjoy your hell at?</qco> </h3><br><br>"
  },
  {
    "html": "<h3> <dco>1.11.20&nbsp; \n9:31 pm</dco> &nbsp;<qco> Would you agree 2x4=rainbow?</qco> </h3><br><br>"
  },
  {
    "html": "<h3> <dco>1.11.20&nbsp; \n9:02 pm</dco> &nbsp;<qco> What is the perfect order to watch the MCU movies?</qco> </h3><br><br>"
  },
  {
    "html": "<h3> <dco>1.11.20&nbsp; \n8:34 pm</dco> &nbsp;<qco> What is the most memorable question on this webpage?</qco> </h3><a href=\"most-memorable-question.php\">this one</a><br><br>"
  },
  {
    "html": "<h3> <dco>1.11.20&nbsp; \n8:28 pm</dco> &nbsp;<qco> i am pretty isolated and lonely but reading and interacting with this page feels a little like making a friendly acquaintance who's trudging along the same road as me for a little while. so like, thanks</qco> </h3><br><br>"
  },
  {
    "html": "<h3> <dco>1.11.20&nbsp; \n8:21 pm</dco> &nbsp;<qco> I'm interested in writing songs but I always get stuck when it comes to the melody. The words are there but I can never really settle on a melody that I think works/that I like. Kinda stuck in a rut. (reference unintentionally intended) Any tips?</qco> </h3><br><br>"
  },
  {
    "html": "<h3> <dco>1.11.20&nbsp; \n8:16 pm</dco> &nbsp;<qco> what is your life goal?</qco> </h3><br><br>"
  },
  {
    "html": "<h3> <dco>1.11.20&nbsp; \n8:09 pm</dco> &nbsp;<qco> settle an argument- what's less of a dinosaur, a pterodactyl or a brontosaurus? </qco></h3>"
  },
  {
    "html": "<h3> <dco>1.11.20&nbsp; \n7:41 pm</dco> &nbsp;<qco> Can you do implicit differentiation on a matter of seconds?</qco></h3>"
  },
  {
    "html": "<h3> <dco>1.11.20&nbsp; \n6:55 pm</dco> &nbsp;<qco> What are your thoughts on actions?&nbsp;</qco> </h3><br><br>"
  },
  {
    "html": "<h3> <dco>1.11.20&nbsp; \n6:54 pm</dco> &nbsp;<qco> Where do you see yourself?</qco> </h3><br><br>"
  },
  {
    "html": "<h3> <dco>1.11.20&nbsp; \n6:49 pm</dco> &nbsp;<qco> How do you know life is real?</qco> </h3><br><br>"
  },
  {
    "html": "<h3> <dco>1.11.20&nbsp; \n6:36 pm</dco> &nbsp;<qco> Did you teach yourself to play the guitar or did you take lessons?</qco> </h3><br><br>"
  },
  {
    "html": "<h3> <dco>1.11.20&nbsp; \n6:25 pm</dco> &nbsp;<qco> what were you doing before making the first music video</qco> </h3><br><br>"
  },
  {
    "html": "<h3> <dco>1.11.20&nbsp; \n6:24 pm</dco> &nbsp;<qco> how do i save myself from condescending vegetables (tomatoes included)&nbsp;</qco> </h3><br><br>"
  },
  {
    "html": "<h3> <dco>1.11.20&nbsp; \n6:22 pm</dco> &nbsp;<qco> whats your favorite way to pick favorites?</qco> </h3><br><br>"
  },
  {
    "html": "<h3> <dco>1.11.20&nbsp; \n6:11 pm</dco> &nbsp;<qco> Hey Bill, I want to learn how to write a 4 brass section part (tenor sax, trombone and a couple of trumpets, correct me if I'm wrong).. do you have any listening suggestion of something \"memorable\" ?\n<br></qco> </h3><i>potent</i><br><br>"
  },
  {
    "html": "<h3> <dco>1.11.20&nbsp; \n5:39 pm</dco> &nbsp;<qco> I am currently in the early stages of recording all my ideas (mostly writing projects, some non-writing projects) into timestamped text files;&nbsp;I have configured a immediate shortcut to do this, etc. I worried I am just recording complete garbage and that it will be impossible to sift through later, not even certain how exactly I will be picking and actioning these things. Are there any recommendable checks, measures, bits of discipline to make this whole process workable?</qco> </h3><a href=\"https://random.org\">random.org</a><br><br>"
  },
  {
    "html": "<h3> <dco>1.11.20&nbsp; \n5:02 pm</dco> &nbsp;<qco> why do birds fly in the business section</qco> </h3><br><br>"
  },
  {
    "html": "<h3> <dco>1.11.20&nbsp; \n4:58 pm</dco> &nbsp;<qco> You can produce insanely deep and subtle harmonies and rhythms, and also have millions of fans. You're among the few who prove that it's possible to touch a big audience without harmonic or rhythmic sacrifice. </qco></h3>"
  },
  {
    "html": "<h3> <dco>1.11.20&nbsp; \n4:58 pm</dco> &nbsp;<qco> Why does food taste like food but only sometimes</qco> </h3><br><br>"
  },
  {
    "html": "<h3> <dco>1.11.20&nbsp; \n4:46 pm</dco> &nbsp;<qco> Is there a way to avoid procrastination?</qco> </h3><br><br>"
  },
  {
    "html": "<h3> <dco>1.11.20&nbsp; \n4:46 pm</dco> &nbsp;<qco> If you could be any number which one would you be&nbsp;&nbsp;</qco></h3>"
  },
  {
    "html": "<h3> <dco>1.11.20&nbsp; \n4:45 pm</dco> &nbsp;<qco> Opinion on birds?</qco> </h3><br><br>"
  },
  {
    "html": "<h3> <dco>1.11.20&nbsp; \n4:42 pm</dco> &nbsp;<qco> What are your thoughts on thoughts?</qco> </h3><br><br>"
  },
  {
    "html": "<h3> <dco>1.11.20&nbsp; \n4:24 pm</dco> &nbsp;<qco> how to start world war h</qco> </h3><br><br>"
  },
  {
    "html": "<h3> <dco>1.11.20&nbsp; \n3:33 pm</dco> &nbsp;<qco> Why is 8 the best number ?</qco> </h3><br><br>"
  },
  {
    "html": "<h3> <dco>1.11.20&nbsp; \n2:29 pm</dco> &nbsp;<qco> Not a question, but La de Da de Da de Da de Day Oh brings me immeasurable joy.&nbsp;</qco> </h3><br><br>"
  },
  {
    "html": "<h3> <dco>1.11.20&nbsp; \n2:25 pm</dco> &nbsp;<qco> How do you feel about reality tv</qco> </h3><br><br>"
  },
  {
    "html": "<h3> <dco>1.11.20&nbsp; \n2:15 pm</dco> &nbsp;<qco> Do you talk a lot in real life?</qco> </h3><br><br>"
  },
  {
    "html": "<h3> <dco>1.11.20&nbsp; \n2:10 pm</dco> &nbsp;<qco> what is your response to those claiming that you have \"dropped off the face of the earth itself\"</qco> </h3><br><br>"
  },
  {
    "html": "<h3> <dco>1.11.20&nbsp; \n1:04 pm</dco> &nbsp;<qco> what is your favorite show on the television</qco> </h3><br><br>"
  },
  {
    "html": "<h3> <dco>1.11.20&nbsp; \n11:57 am</dco> &nbsp;<qco> What is your honest, non-biased opinion on potatoes?</qco> </h3><br><br>"
  },
  {
    "html": "<h3> <dco>1.11.20&nbsp; \n11:27 am</dco> &nbsp;<qco> how be smart</qco> </h3><br><br>"
  },
  {
    "html": "<h3> <dco>1.11.20&nbsp; \n11:25 am</dco> &nbsp;<qco> If I wanted to transend humanity, what would I have to do?</qco> </h3><br><br>"
  },
  {
    "html": "<h3> <dco>1.11.20&nbsp; \n11:24 am</dco> &nbsp;<qco> Do you get these questions</qco> </h3><br><br>"
  },
  {
    "html": "<h3> <dco>1.11.20&nbsp; \n11:22 am</dco> &nbsp;<qco> what is your religion</qco> </h3><br><br>"
  },
  {
    "html": "<h3> <dco>1.11.20&nbsp; \n11:18 am</dco> &nbsp;<qco> favorite work of art that doesn't exist?</qco> </h3><br><br>"
  },
  {
    "html": "<h3> <dco>1.11.20&nbsp; \n11:10 am</dco> &nbsp;<qco> Why is the world flat</qco> </h3><br><br>"
  },
  {
    "html": "<h3> <dco>1.11.20&nbsp; \n11:07 am</dco> &nbsp;<qco> whats your favorite color that isn't a color but also kinda is</qco> </h3><br><br>"
  },
  {
    "html": "<h3> <dco>1.11.20&nbsp; \n10:59 am</dco> &nbsp;<qco> are you alive</qco> </h3><br><br>"
  },
  {
    "html": "<h3> <dco>1.11.20&nbsp; \n10:56 am</dco> &nbsp;<qco> hey bill, how would you describe the change in melody after the lyrics \"and it goes along\" at the end of \"and the day goes on\"?</qco></h3>"
  },
  {
    "html": "<h3> <dco>1.11.20&nbsp; \n10:54 am</dco> &nbsp;<qco> How can a speeding bullet be speeding? </qco></h3>"
  }
]
