[
  {
    "html": "<h3> <dco>2.10.25&nbsp; \n2:13 am</dco> &nbsp;<qco> do you think the universe realized one day that it wanted to be there so then poof there it was?</qco> </h3>"
  },
  {
    "html": "<h3> <dco>2.10.25&nbsp; \n1:23 am</dco> &nbsp;<qco> I'm in a poetry class but I feel like everything I write is stupid. I've tried the strategy of writing stupid stuff on purpose, but then I feel creatively unfulfilled, like no one is taking my work or my abilities seriously. H e l p</qco> </h3>"
  },
  {
    "html": "<h3> <dco>2.10.25&nbsp; \n1:18 am</dco> &nbsp;<qco> Why is the word \"whose\" also used for inanimate objects?</qco> </h3>"
  },
  {
    "html": "<h3> <dco>2.10.25&nbsp; \n12:21 am</dco> &nbsp;<qco> Why is the 7 train your favorite MTA subway line?</qco></h3><h3><qco> &nbsp;&nbsp;&nbsp;&nbsp;&nbsp; By the way, what did you think of the Hudson Yards station when it opened?</qco> </h3>"
  },
  {
    "html": "<h3> <dco>2.9.25&nbsp; \n11:50 pm</dco> &nbsp;<qco> Do you like Sonic?</qco> </h3>"
  },
  {
    "html": "<h3> <dco>2.9.25&nbsp; \n11:34 pm</dco> &nbsp;<qco> How to interact with human beings in a normal way. I am secretly a tractor</qco> </h3>"
  },
  {
    "html": "<h3> <dco>2.9.25&nbsp; \n11:17 pm</dco> &nbsp;<qco> What's your favorite cat toy?</qco> </h3>"
  },
  {
    "html": "<h3> <dco>2.9.25&nbsp; \n10:23 pm</dco> &nbsp;<qco> How to make things go back to the way they once were?</qco> </h3>"
  },
  {
    "html": "<h3> <dco>2.9.25&nbsp; \n9:45 pm</dco> &nbsp;<qco> am i allowed to think?</qco> </h3>"
  },
  {
    "html": "<h3> <dco>2.9.25&nbsp; \n8:52 pm</dco> &nbsp;<qco> It dawned on me today that I'm further from achieving my personal goals than I was a decade ago, and I don't know how to cope with that</qco> </h3>"
  },
  {
    "html": "<h3> <dco>2.9.25&nbsp; \n8:22 pm</dco> &nbsp;<qco> Everyday I try to sort my life out, but when the sun sets I find out it was me that was out of order. Do you know this feeling?</qco> </h3>"
  },
  {
    "html": "<h3> <dco>2.9.25&nbsp; \n7:55 pm</dco> &nbsp;<qco> for sometime now, i'm inmagining myself hiring a band that is spontaneous at doing anything because i'm going to hire them to play your songs with me singing it. and i want them to recreate every bit of instruments as much as possible as that's what makes me groove with it. do you think it's a good idea? what advice do you have to give me if i'm going to execute this idea?</qco> </h3>"
  },
  {
    "html": "<h3> <dco>2.9.25&nbsp; \n7:40 pm</dco> &nbsp;<qco> what if cars could fly</qco> </h3>"
  },
  {
    "html": "<h3> <dco>2.9.25&nbsp; \n6:56 pm</dco> &nbsp;<qco> What do you think about a G7 chord except I added a C# and Eb next to the D?</qco> </h3>"
  },
  {
    "html": "<h3> <dco>2.9.25&nbsp; \n6:38 pm</dco> &nbsp;<qco> Are you watching / going to watch the Super Bowl :3</qco> </h3>"
  },
  {
    "html": "<h3> <dco>2.9.25&nbsp; \n5:57 pm</dco> &nbsp;<qco> Is free will a concept explorable with scientific tools?</qco> </h3>"
  },
  {
    "html": "<h3> <dco>2.9.25&nbsp; \n5:38 pm</dco> &nbsp;<qco> the one true religion?</qco> </h3>"
  },
  {
    "html": "<h3> <dco>2.9.25&nbsp; \n4:47 pm</dco> &nbsp;<qco> I don't know if I can get a hold of you but I have a question for you about the car that I have for you and I need to know if you have a car that you can borrow from me. \n<br>\n<br>Sorry i fell asleep on the predictive text button.</qco> </h3>"
  },
  {
    "html": "<h3> <dco>2.9.25&nbsp; \n3:09 pm</dco> &nbsp;<qco> does the random question button give fully random questions or is it weighted in some way?</qco> </h3>"
  },
  {
    "html": "<h3> <dco>2.9.25&nbsp; \n2:50 pm</dco> &nbsp;<qco> have you never</qco> </h3>"
  },
  {
    "html": "<h3> <dco>2.9.25&nbsp; \n2:47 pm</dco> &nbsp;<qco> If you had to name a random object in your house, which object would it be and what name would you choose?</qco> </h3>"
  },
  {
    "html": "<h3> <dco>2.9.25&nbsp; \n1:14 pm</dco> &nbsp;<qco> Do clowns have free will?</qco> </h3>"
  },
  {
    "html": "<h3> <dco>2.9.25&nbsp; \n1:12 pm</dco> &nbsp;<qco> how long does it normally take for u to get to a question? like how far back is the current batch you're answering from?</qco> </h3>"
  },
  {
    "html": "<h3> <dco>2.9.25&nbsp; 11:52 am</dco> &nbsp;<qco> why is everything so dumb and stupid</qco> </h3>"
  },
  {
    "html": "<h3> <dco>2.9.25&nbsp; \n10:25 am</dco> &nbsp;<qco> if a circle has infinite sides then a square is also a circle because a square has 4 sides and 4 is part of infinity</qco> </h3>"
  },
  {
    "html": "<h3> <dco>2.9.25&nbsp; \n6:52 am</dco> &nbsp;<qco> orangutan or horse? (elaborate)</qco> </h3>"
  },
  {
    "html": "<h3> <dco>2.9.25&nbsp; \n5:34 am</dco> &nbsp;<qco> how should I fix my sleep schedule</qco> </h3>"
  },
  {
    "html": "<h3> <dco>2.9.25&nbsp; \n3:26 am</dco> &nbsp;<qco> What happens before after we die?</qco> </h3>"
  },
  {
    "html": "<h3> <dco>2.9.25&nbsp; \n2:59 am</dco> &nbsp;<qco> what was the last thing that you took personally?</qco> </h3>"
  },
  {
    "html": "<h3> <dco>2.9.25&nbsp; \n2:26 am</dco> &nbsp;<qco> can you explain what a filibuster is</qco> </h3>"
  },
  {
    "html": "<h3> <dco>2.9.25&nbsp; \n1:40 am</dco> &nbsp;<qco> Is it okay to say hi to you if I see you on the street</qco> </h3>"
  },
  {
    "html": "<h3> <dco>2.9.25&nbsp; \n1:33 am</dco> &nbsp;<qco> I keep writing songs with melodies that are outside my singing range and then become too attached to them to change them, so I tell myself I'll hire a professional singer eventually but really they just never get produced. How do I stop doing this to myself</qco> </h3>"
  },
  {
    "html": "<h3> <dco>2.9.25&nbsp; 1:07 am</dco> &nbsp;<qco> What kind of questions do you prefer to answer here?</qco> </h3>"
  },
  {
    "html": "<h3> <dco>2.9.25&nbsp; \n12:45 am</dco> &nbsp;<qco> What are your thoughts on rap music? In general?</qco> </h3>"
  },
  {
    "html": "<h3> <dco>2.9.25&nbsp; \n12:03 am</dco> &nbsp;<qco> how to deal with opening my project, making one frame of the video and then giving up for the day?</qco> </h3>"
  },
  {
    "html": "<h3> <dco>2.8.25&nbsp; 11:55 pm</dco> &nbsp;<qco> do you enjoy pineapple on pizza?</qco> </h3>"
  },
  {
    "html": "<h3> <dco>2.8.25&nbsp; \n11:49 pm</dco> &nbsp;<qco> favourite dinosaur?</qco> </h3>"
  },
  {
    "html": "<h3> <dco>2.8.25&nbsp; 11:05 pm</dco> &nbsp;<qco> Do you like music?</qco> </h3>"
  },
  {
    "html": "<h3> <dco>2.8.25&nbsp; \n10:59 pm</dco> &nbsp;<qco> how often are you intentionally ambiguous?</qco> </h3>"
  },
  {
    "html": "<h3> <dco>2.8.25&nbsp; \n10:15 pm</dco> &nbsp;<qco> If you could invent a new color, what would you call it?</qco> </h3>"
  },
  {
    "html": "<h3> <dco>2.8.25&nbsp; \n9:31 pm</dco> &nbsp;<qco> What is the optimal way to say \"hmmmmm\"?</qco> </h3>"
  },
  {
    "html": "<h3> <dco>2.8.25&nbsp; \n7:48 pm</dco> &nbsp;<qco> In Mount st helens is about to blow up, when you sing \"we'll never slow down,\" is that a litle callback/reference to your song slow down? I've always thought so but then was talking to someone recently and mentioned it, but they said it was just coincidence&nbsp;</qco> </h3>"
  },
  {
    "html": "<h3> <dco>2.8.25&nbsp; 7:31 pm</dco> &nbsp;<qco> what if i dont want to ask a question</qco> </h3>"
  },
  {
    "html": "<h3> <dco>2.8.25&nbsp; \n6:44 pm</dco> &nbsp;<qco> if you could be named after anything in the world, what would it be</qco> </h3>"
  },
  {
    "html": "<h3> <dco>2.8.25&nbsp; \n6:40 pm</dco> &nbsp;<qco> what are your thoughts on French fries?\n<br></qco> </h3>"
  },
  {
    "html": "<h3> <dco>2.8.25&nbsp; \n5:54 pm</dco> &nbsp;<qco> Did you know that 10+9+8+7+6+5+4+3+2+1 equals infinity?</qco> </h3>"
  },
  {
    "html": "<h3> <dco>2.8.25&nbsp; \n4:41 pm</dco> &nbsp;<qco> how to stop happiness attacks?</qco> </h3>"
  },
  {
    "html": "<h3> <dco>2.8.25&nbsp; \n3:24 pm</dco> &nbsp;<qco> Could you help me with nothing in particular?</qco> </h3>"
  },
  {
    "html": "<h3> <dco>2.8.25&nbsp; \n2:44 pm</dco> &nbsp;<qco> Do you think you could drive trains around?</qco> </h3>"
  },
  {
    "html": "<h3> <dco>2.8.25&nbsp; \n1:05 pm</dco> &nbsp;<qco> do you practice the language you're learning every day? of course i mean dutch, etc., not the languages of english, music, or love</qco> </h3>"
  }
]
