[
  {
    "html": "<h3> <dco>2.27.18&nbsp;\n8:56 am</dco> &nbsp;<qco> where did you post your songs or videos online before you started uploading them to youtube?</qco> </h3>      billwurtz dot com\n<br><br>"
  },
  {
    "html": "<h3> <dco>2.27.18&nbsp;\n6:03 am</dco> &nbsp;<qco> I have recently learned to look at my pain as a rejecting reaction toward disorder in the world. I then choose to accept the disorder, for the sake of understanding it and truly learning how to put it into order, instead of fighting it. In your opinion, what is the secret to Learning?</qco> </h3>      experience\n<br><br>"
  },
  {
    "html": "<h3> <dco>2.27.18&nbsp;\n2:05 am</dco> &nbsp;<qco> may you please give me one (1) tip about life</qco> </h3>      i have given hundreds, throughout this page and the entire site, and elsewhere as well. check some of them out and let me know if you need more, but i will be making more, regardless\n<br><br>"
  },
  {
    "html": "<h3> <dco>2.27.18&nbsp;\n2:01 am</dco> &nbsp;<qco> what makes a person Bad</qco> </h3>      if they are too good\n<br><br>"
  },
  {
    "html": "<h3> <dco>2.27.18&nbsp;\n1:57 am</dco> &nbsp;<qco> Do you have any interest in creating intentional ASMR? \n</qco></h3>      you mean the African Sex Mating Ritual? oh hell yeah<h3> <qco> &nbsp;&nbsp;&nbsp;&nbsp;&nbsp;Your jingles and sound effects are incredibly satisfying.</qco> </h3>      \n<br><br>"
  },
  {
    "html": "<h3> <dco>2.27.18&nbsp;\n1:16 am</dco> &nbsp;<qco> Grow a moustache. It would be crazy, you'd break the internet.&nbsp;</qco> </h3>      if mustaches broke the internet the ineternet would be broken already\n<br><br>"
  },
  {
    "html": "<h3> <dco>2.27.18&nbsp;\n12:54 am</dco> &nbsp;<qco> would you currently have any use for an american football?</qco> </h3>      sure\n<br><br>"
  },
  {
    "html": "<h3> <dco>2.27.18&nbsp;\n12:41 am</dco> &nbsp;<qco> Do you ever feel, like, limited by your options for communication? Like, a person can have so many different nuanced thoughts but they can only say so much with their voice and their body, right?</qco> </h3>      trying to express everything with limited tools is the name of the game\n<br><br>"
  },
  {
    "html": "<h3> <dco>2.27.18&nbsp;\n12:13 am</dco> &nbsp;<qco> if a baby had been conceived in the moment HOTEWIG was released, It would be a week and a half overdue today. neat eh?</qco> </h3>      if they had been born when the video was releasd, they would have been conceived yet still after i was already working on it\n<br><br>"
  },
  {
    "html": "<h3> <dco>2.27.18&nbsp;\n12:08 am</dco> &nbsp;<qco> what if god is real, and he hates me!</qco> </h3>      that sounds like something the fake god would do\n<br><br>"
  },
  {
    "html": "<h3> <dco>2.26.18&nbsp;\n11:52 pm</dco> &nbsp;<qco> how do i feel?</qco> </h3>      i don't know\n<br><br>"
  },
  {
    "html": "<h3> <dco>2.26.18&nbsp;\n11:51 pm</dco> &nbsp;<qco> what's your favorite love story?</qco> </h3>      the big bang\n<br><br>"
  },
  {
    "html": "<h3> <dco>2.26.18&nbsp;\n11:19 pm</dco> &nbsp;<qco> When making hotewig and hoj, how did you decide which parts would get \"jingles\"? \n</qco></h3>      it's kind of like knowing when it's time to wear a jacket and when to wear just a light sweatshirt<h3> <qco> &nbsp;&nbsp;&nbsp;&nbsp;&nbsp;Did you write the scripts knowing that certain parts would be jingles, </qco></h3>      yes<h3> <qco> &nbsp;&nbsp;&nbsp;&nbsp;&nbsp;or did you just write the scripts and then decide which would be jingles when you wrote the music?</qco> </h3>      absolutely not\n<br><br>"
  },
  {
    "html": "<h3> <dco>2.26.18&nbsp;\n11:05 pm</dco> &nbsp;<qco> hey so i have recently been exploring your website. i really enjoy your reality videos. do you think you will make more reality videos in the future?\n<br></qco> </h3>      yes\n<br><br>"
  },
  {
    "html": "<h3> <dco>2.26.18&nbsp;\n11:02 pm</dco> &nbsp;<qco> I wish you answered questions in a more genuine and heartfelt way, even if that means answering less\n<br></qco> </h3>      \ni wish you were able to perceive how genuine this page is\n\n<br>       \n<br><br>"
  },
  {
    "html": "<h3> <dco>2.26.18&nbsp;\n10:58 pm</dco> &nbsp;<qco> How often should I practice guitar&nbsp;</qco> </h3>      what are you practicing for\n<br><br>"
  },
  {
    "html": "<h3> <dco>2.26.18&nbsp;\n10:51 pm</dco> &nbsp;<qco> How many times you answer question by \"ah #relatable\"?</qco> </h3>      57\n<br><br>"
  },
  {
    "html": "<h3> <dco>2.26.18&nbsp;\n10:34 pm</dco> &nbsp;<qco> why do humans have to have negative emotions? and how can we get rid of them?</qco> </h3>      if you did, your better emotions would seem more average, and your previously average emotions will feel terrible\n<br><br>"
  },
  {
    "html": "<h3> <dco>2.26.18&nbsp;\n10:19 pm</dco> &nbsp;<qco> what is the most experimental thing you think you've ever done</qco> </h3>      was born\n<br><br>"
  },
  {
    "html": "<h3> <dco>2.26.18&nbsp;\n10:17 pm</dco> &nbsp;<qco> How should I come out to my parents?</qco> </h3>      how did they come out to you\n\n<br><br>"
  },
  {
    "html": "<h3> <dco>2.26.18&nbsp;\n9:48 pm</dco> &nbsp;<qco> why is the earth flat?</qco> </h3>      maybe because you are viewing it in a 2d medium\n<br><br>"
  },
  {
    "html": "<h3> <dco>2.26.18&nbsp;\n9:46 pm</dco> &nbsp;<qco> Why are so many of your songs about going home?</qco> </h3>      it just seems like a nice thing, for songs<br><br>"
  },
  {
    "html": "<h3> <dco>2.26.18&nbsp;\n9:40 pm</dco> &nbsp;<qco> Any suggestions for the Pittsburg zoo?</qco> </h3>      animals?\n<br><br>"
  },
  {
    "html": "<h3> <dco>2.26.18&nbsp;\n8:33 pm</dco> &nbsp;<qco> what is it like to be human?</qco> </h3>      seems familiar\n<br><br>"
  },
  {
    "html": "<h3> <dco>2.26.18&nbsp;\n8:17 pm</dco> &nbsp;<qco> what is the most despicable thing someone can do at a social gathering?</qco> </h3>      destroy the entire universe\n<br><br>"
  },
  {
    "html": "<h3> <dco>2.26.18&nbsp;\n7:24 pm</dco> &nbsp;<qco> do you find the phrase \"call and response\" useful? </qco></h3>      not really<h3> <qco> &nbsp;&nbsp;&nbsp;&nbsp;&nbsp;i just find it confusing. i mean, with the right lyrics i can make anything be a response to any call</qco> </h3>      that's true\n<br><br>"
  },
  {
    "html": "<h3> <dco>2.26.18&nbsp;\n7:00 pm</dco> &nbsp;<qco> Why do you believe you have free will?</qco></h3>      why would i not<h3> <qco> &nbsp;&nbsp;&nbsp;&nbsp;&nbsp; Asking because I would enjoy believing in free will.</qco> </h3>      \n<br><br>"
  },
  {
    "html": "<h3> <dco>2.26.18&nbsp;\n6:19 pm</dco> &nbsp;<qco> are you planning on updating the reality page in the recent future?</qco> </h3>      sure\n<br><br>"
  },
  {
    "html": "<h3> <dco>2.26.18&nbsp;\n6:17 pm</dco> &nbsp;<qco> I just finished watching the entire reality page. will there be more journal entries here, or is this questions page serving as the second generation of such an endeavor?</qco> </h3>      the questions page has been here since before the reality page was made\n\n<br><br>"
  },
  {
    "html": "<h3> <dco>2.26.18&nbsp;\n5:24 pm</dco> &nbsp;<qco> How does one such as yourself get invited to vidcon? I don't think you applied to, did vidcon come up to you and ask you to be a part of it?</qco> </h3>      they sent it via electronic mail (e-mail)\n<br><br>"
  },
  {
    "html": "<h3> <dco>2.26.18&nbsp;\n5:21 pm</dco> &nbsp;<qco> what is boring?</qco> </h3>      different things may bore different people\n<br><br>"
  },
  {
    "html": "<h3> <dco>2.26.18&nbsp;\n5:17 pm</dco> &nbsp;<qco> is your new thing a cover of michael jackson?</qco> </h3>      no\n<br><br>"
  },
  {
    "html": "<h3> <dco>2.26.18&nbsp;\n5:06 pm</dco> &nbsp;<qco> does all water taste the same?</qco> </h3>      no\n<br><br>"
  },
  {
    "html": "<h3> <dco>2.26.18&nbsp;\n4:31 pm</dco> &nbsp;<qco> 1\n<br>2\n<br>3\n<br>4\n<br>5\n<br>6\n<br>7</qco> </h3>      ah, i think i see where you're going with this\n<br><br>"
  },
  {
    "html": "<h3> <dco>2.26.18&nbsp;\n3:56 pm</dco> &nbsp;<qco> What is \"difficult\" in music?</qco></h3>      you'll have to try and see<h3> <qco> &nbsp;&nbsp;&nbsp;&nbsp;&nbsp; How do we classify a piece as difficult? </qco></h3>      if something is difficult for you, then just call it difficult. or call it easy, for a twist<h3> <qco> &nbsp;&nbsp;&nbsp;&nbsp;&nbsp;What is difficult to you?</qco> </h3>      getting that unexplicable 'lump' out of the 250hz range, in the final mix. although i am rapidly learning some tricks \n<br><br>"
  },
  {
    "html": "<h3> <dco>2.26.18&nbsp;\n2:56 pm</dco> &nbsp;<qco> what is the solution to climate change</qco> </h3>      keeping the climate the same?\n<br><br>"
  },
  {
    "html": "<h3> <dco>2.26.18&nbsp;\n2:36 pm</dco> &nbsp;<qco> Do you live on Mars?</qco> </h3>      no\n<br><br>"
  },
  {
    "html": "<h3> <dco>2.26.18&nbsp;\n2:25 pm</dco> &nbsp;<qco> <a href=\"q.php?date=201802260143\">2.26.18&nbsp;&nbsp;1:43 am</a>  oh my please do tell me some of what youve learned! i know you like to be wry and cagey but as a social scientist this stuff is really fascinating to me! might not ever get to see myself</qco> </h3>      <a href=\"q.php?date=201608252321\">8.25.16&nbsp;&nbsp;11:21 pm</a><br><br>"
  },
  {
    "html": "<h3> <dco>2.26.18&nbsp;\n2:15 pm</dco> &nbsp;<qco> Do you try to be nice to the ad company people that contact you to try and convince you to put ads on your website/videos? Or do you just ignore them, or how do you handle it?</qco> </h3>      it's mostly robots actually\n<br><br>"
  },
  {
    "html": "<h3> <dco>2.26.18&nbsp;\n2:12 pm</dco> &nbsp;<qco> do a lot of people buy your song off of itunes and platforms like that</qco> </h3>      yes\n<br><br>"
  },
  {
    "html": "<h3> <dco>2.26.18&nbsp;\n2:11 pm</dco> &nbsp;<qco> Wait but so have you actually seriously studied linguistics? </qco></h3>      all day bro<h3> <qco> &nbsp;&nbsp;&nbsp;&nbsp;&nbsp;\nSome of the things you say and come up with make me think you have and that you're being playful with semantics sorta like Lewis carol lol. I could point to some specific examples but as a linguist I was just curious.&nbsp;</qco> </h3>      <br><br>"
  },
  {
    "html": "<h3> <dco>2.26.18&nbsp;\n1:29 pm</dco> &nbsp;<qco> If the universe is an endless void and the earth spins counterclockwise, what color is my shirt?</qco> </h3>      there would be no shirt\n<br><br>"
  },
  {
    "html": "<h3> <dco>2.26.18&nbsp;\n12:20 pm</dco> &nbsp;<qco> why u never uses capital letters</qco> </h3>      PERHAPS YOU COULD ASK YOURSELF THAT\n<br><br>"
  },
  {
    "html": "<h3> <dco>2.26.18&nbsp;\n10:57 am</dco> &nbsp;<qco> do you use iambic pentameter?</qco> </h3>      not exclusively\n<br><br>"
  },
  {
    "html": "<h3> <dco>2.26.18&nbsp;\n10:38 am</dco> &nbsp;<qco> What is some good advice so that I may live my life in a way that is better than the way I'm currently living my life?</qco> </h3>      you forgot to say how you are currently doing it\n<br><br>"
  },
  {
    "html": "<h3> <dco>2.26.18&nbsp;\n9:42 am</dco> &nbsp;<qco> i have this early memory from kindergarten that has puzzled me for years. maybe you'll be able to decipher it? (idk if u want to read this, it's kinda long)\n<br>the teacher is at the board. she writes \"dogs\" on the top left. she then asks us to brainstorm any ideas relating to 'dogs'. of course, every kid in the room immediately shouts out their answers ('ball' 'park' 'bark' 'fur' 'cuddles'). she writes all of their answers on the board, hardly leaving any room on the right side.\n<br>then, she puts the word \"Thailand\" on the right. no one can come up with any ideas other than 'food'. and that's where the memory ends for me.\n<br>what do you think the teacher was trying to explain with this example?</qco> </h3>      it sounds like you might be combining elements of 2 different memories. or perhaps 'thailand' was not a starting word, but one of the responses\n<br><br>"
  },
  {
    "html": "<h3> <dco>2.26.18&nbsp;\n9:22 am</dco> &nbsp;<qco> I only got 1 hour of sleep help</qco> </h3>      sleep more?\n<br><br>"
  },
  {
    "html": "<h3> <dco>2.26.18&nbsp;\n8:38 am</dco> &nbsp;<qco> How to make life not as boring?</qco> </h3>      what was the least boring thing you did or saw, in the last 10 days? there are clues there\n<br><br>"
  },
  {
    "html": "<h3> <dco>2.26.18&nbsp;\n8:17 am</dco> &nbsp;<qco> why is 'spicy' such a good word to describe almost anything positive?</qco> </h3>      i disagree<br><br>"
  },
  {
    "html": "<h3> <dco>2.26.18&nbsp;\n8:00 am</dco> &nbsp;<qco> What did you do to get where you are now?</qco> </h3>      start expressing myself ruthlessly and relentlessly in viewable/readable/listenable mediums, with no plans of ever stopping\n<br><br>"
  }
]
