[
  {
    "html": "<h3> <dco>4.25.18&nbsp; \n4:54 pm</dco> &nbsp;<qco> why do i feel like i am in a loop and how do i get out of it</qco> </h3><br><br>"
  },
  {
    "html": "<h3> <dco>4.25.18&nbsp; \n4:53 pm</dco> &nbsp;<qco> Are you going to make a blog some day? maybe a Q&amp;A with your music?</qco> </h3><br><br>"
  },
  {
    "html": "<h3> <dco>4.25.18&nbsp; \n4:47 pm</dco> &nbsp;<qco> Is 'whenst' a real word?</qco> </h3><br><br>"
  },
  {
    "html": "<h3> <dco>4.25.18&nbsp; \n4:46 pm</dco> &nbsp;<qco> whats your favourite ascii character</qco> </h3><br><br>"
  },
  {
    "html": "<h3> <dco>4.25.18&nbsp; \n4:45 pm</dco> &nbsp;<qco> When will your next big video come out</qco> </h3><br><br>"
  },
  {
    "html": "<h3> <dco>4.25.18&nbsp; \n4:45 pm</dco> &nbsp;<qco> Can we get wurtz murch</qco> </h3><a href=\"http://billwurtz.myshopify.com\">sure</a><br><br>"
  },
  {
    "html": "<h3> <dco>4.25.18&nbsp; \n4:44 pm</dco> &nbsp;<qco> I love the brightness and catchiness of \"And The Day Goes On\"! Is it intended as a kind of follow-up to \"La De Da...\", or am I making up things in my head again?</qco> </h3><br><br>"
  },
  {
    "html": "<h3> <dco>4.25.18&nbsp; \n4:41 pm</dco> &nbsp;<qco> you said the new video would not involve fences</qco></h3><h3> <qco> &nbsp;&nbsp;&nbsp;&nbsp;&nbsp; but if you pause the video at 0:24 you can clearly see a fence</qco> </h3><br><br>"
  },
  {
    "html": "<h3> <dco>4.25.18&nbsp; \n4:36 pm</dco> &nbsp;<qco> Hi I am from the planet Mercury\n</qco></h3><h3> <qco> &nbsp;&nbsp;&nbsp;&nbsp;&nbsp;\n and the video you posted is very offensive because our planet rotates slower than yours.\n</qco></h3><h3> <qco> &nbsp;&nbsp;&nbsp;&nbsp;&nbsp;\n Please remove it from your channel. Thank you.</qco> </h3><br><br>"
  },
  {
    "html": "<h3> <dco>4.25.18&nbsp; \n4:36 pm</dco> &nbsp;<qco> is this the first question since the new song came out</qco> </h3><br><br>"
  },
  {
    "html": "<h3> <dco>4.25.18&nbsp; \n4:36 pm</dco> &nbsp;<qco> I keep blaming people of opposing political views for all of the problems in the world, but the problems are still there!!!! How do I fix this conundrum?\n<br></qco> </h3><br><br>"
  },
  {
    "html": "<h3> <dco>4.25.18&nbsp; \n4:36 pm</dco> &nbsp;<qco> what's your favorite emoji?</qco> </h3><br><br>"
  },
  {
    "html": "<h3> <dco>4.25.18&nbsp; \n4:35 pm</dco> &nbsp;<qco> when is the day goes on gonna be on itunes?</qco> </h3><br><br>"
  },
  {
    "html": "<h3> <dco>4.25.18&nbsp; \n4:33 pm</dco> &nbsp;<qco> Does the reoccuring theme of going home have a special meaning to you?</qco> </h3><br><br>"
  },
  {
    "html": "<h3> <dco>4.25.18&nbsp; \n4:28 pm</dco> &nbsp;<qco> In the \"and the day goes on\" video you say you're thinking about the future\n</qco></h3><h3> <qco> &nbsp;&nbsp;&nbsp;&nbsp;&nbsp;\n and then you start talking about 1900. Is this proof you live in 1899?</qco> </h3><br><br>"
  },
  {
    "html": "<h3> <dco>4.25.18&nbsp; \n4:27 pm</dco> &nbsp;<qco> How do you know when to use 2 or 9, 4 or 11, and 6 or 13 in a chord name?\n</qco></h3><h3> <qco> &nbsp;&nbsp;&nbsp;&nbsp;&nbsp;\n Sometimes it's obvious if you just have the stack of thirds (1,3,5,7,9,11,13)... but what about when the chord isn't built in numerical order like that? \n</qco></h3><h3> <qco> &nbsp;&nbsp;&nbsp;&nbsp;&nbsp;\nFor example, I have this song where for an E7 I play the notes D F# G# B (all in the same octave).. would that just be called E9 even though there's no root and the F# isn't in a higher octave?</qco> </h3><br><br>"
  },
  {
    "html": "<h3> <dco>4.25.18&nbsp; \n3:56 pm</dco> &nbsp;<qco> hey bill I was listening to the song \"hey baby, buy my car\", located on the 'songs\" page on the Bill Wurtz Website, and I noticed your voice sounds slightly higher than normal. Was it edited?</qco> </h3><br><br>"
  },
  {
    "html": "<h3> <dco>4.25.18&nbsp; \n2:41 pm</dco> &nbsp;<qco> how's the housing market on jupiter</qco> </h3><br><br>"
  },
  {
    "html": "<h3> <dco>4.25.18&nbsp; \n2:35 pm</dco> &nbsp;<qco> how do i stop hating my friends&nbsp;</qco> </h3><br><br>"
  },
  {
    "html": "<h3> <dco>4.25.18&nbsp; \n2:34 pm</dco> &nbsp;<qco> do you recommend watching your videos while high</qco> </h3><br><br>"
  },
  {
    "html": "<h3> <dco>4.25.18&nbsp; \n2:20 pm</dco> &nbsp;<qco> When you write the number 5, do you start from the top-right or bottom-left?</qco> </h3><br><br>"
  },
  {
    "html": "<h3> <dco>4.25.18&nbsp; \n2:16 pm</dco> &nbsp;<qco> What's your favorite sandwich?</qco> </h3><br><br>"
  },
  {
    "html": "<h3> <dco>4.25.18&nbsp; \n12:53 pm</dco> &nbsp;<qco> name me</qco> </h3><br><br>"
  },
  {
    "html": "<h3> <dco>4.25.18&nbsp; \n12:24 pm</dco> &nbsp;<qco> You said 'everything makes sense', but what about nonsense?&nbsp;</qco> </h3><br><br>"
  },
  {
    "html": "<h3> <dco>4.25.18&nbsp; \n11:22 am</dco> &nbsp;<qco> why do we paint eggs on easter?</qco> </h3><br><br>"
  },
  {
    "html": "<h3> <dco>4.25.18&nbsp; \n11:09 am</dco> &nbsp;<qco> <a href=\"q.php?date=201804241908\">4.24.18&nbsp;&nbsp;7:08 pm</a>  wait, you wrote a song DURING the production of history of the entire world?</qco> </h3><br><br>"
  },
  {
    "html": "<h3> <dco>4.25.18&nbsp; \n10:39 am</dco> &nbsp;<qco> whats for lunch?</qco> </h3><br><br>"
  },
  {
    "html": "<h3> <dco>4.25.18&nbsp; \n10:38 am</dco> &nbsp;<qco> how often do you lose track?</qco> </h3><br><br>"
  },
  {
    "html": "<h3> <dco>4.25.18&nbsp; \n10:38 am</dco> &nbsp;<qco> Why is time so stupid?</qco> </h3><br><br>"
  },
  {
    "html": "<h3> <dco>4.25.18&nbsp; \n10:36 am</dco> &nbsp;<qco> where do we draw the line with meatloaf?</qco> </h3><br><br>"
  },
  {
    "html": "<h3> <dco>4.25.18&nbsp; \n10:33 am</dco> &nbsp;<qco> how do i use hexadecimals?</qco> </h3><br><br>"
  },
  {
    "html": "<h3> <dco>4.25.18&nbsp; \n10:30 am</dco> &nbsp;<qco> what's best?</qco> </h3><br><br>"
  },
  {
    "html": "<h3> <dco>4.25.18&nbsp; \n10:27 am</dco> &nbsp;<qco> do you know how to count to 27898765?</qco> </h3><br><br>"
  },
  {
    "html": "<h3> <dco>4.25.18&nbsp; \n10:24 am</dco> &nbsp;<qco> how realistic were the toy story movies really?</qco> </h3><br><br>"
  },
  {
    "html": "<h3> <dco>4.25.18&nbsp; \n9:42 am</dco> &nbsp;<qco> have you ever thought of doing a second unboxing video? i think your first one was very popular</qco> </h3><br><br>"
  },
  {
    "html": "<h3> <dco>4.25.18&nbsp; \n9:31 am</dco> &nbsp;<qco> do you sell soap</qco> </h3><br><br>"
  },
  {
    "html": "<h3> <dco>4.25.18&nbsp; \n9:16 am</dco> &nbsp;<qco> what do you do when you receive a question here that gives you too many feelings</qco> </h3><br><br>"
  },
  {
    "html": "<h3> <dco>4.25.18&nbsp; \n7:19 am</dco> &nbsp;<qco> how do i make a sandwitch</qco> </h3><br><br>"
  },
  {
    "html": "<h3> <dco>4.25.18&nbsp; \n7:19 am</dco> &nbsp;<qco> I like egg?</qco> </h3><br><br>"
  },
  {
    "html": "<h3> <dco>4.25.18&nbsp; \n6:50 am</dco> &nbsp;<qco> the moon is made out of cheese</qco> </h3><br><br>"
  },
  {
    "html": "<h3> <dco>4.25.18&nbsp; \n6:15 am</dco> &nbsp;<qco> hey bill what were your sources for the first minute of thotewig? especially the where when what stuff.. this is important to me.. please answer thanks in advance</qco> </h3><br><br>"
  },
  {
    "html": "<h3> <dco>4.25.18&nbsp; \n6:09 am</dco> &nbsp;<qco> Why is the earth flat? \n</qco></h3><h3> <qco> &nbsp;&nbsp;&nbsp;&nbsp;&nbsp;\nAnd if the earth is flat, what is on the other side of the earth?</qco> </h3><br><br>"
  },
  {
    "html": "<h3> <dco>4.25.18&nbsp; \n4:25 am</dco> &nbsp;<qco> Can we expect any vinyl pressings of your stuff anytime soon? </qco></h3><h3> <qco> &nbsp;&nbsp;&nbsp;&nbsp;&nbsp;Or even just a proper full length debut?</qco> </h3><br><br>"
  },
  {
    "html": "<h3> <dco>4.25.18&nbsp; \n12:46 am</dco> &nbsp;<qco> how is mars</qco> </h3><br><br>"
  },
  {
    "html": "<h3> <dco>4.24.18&nbsp; \n11:40 pm</dco> &nbsp;<qco> If I sign my questions, will it help to build a greater bond between Me, the asking party, and You, answering party? Or will the lack of anonymity ruin the dynamic? Sincerely- Jules\n<br></qco> </h3><br><br>"
  },
  {
    "html": "<h3> <dco>4.24.18&nbsp; \n11:07 pm</dco> &nbsp;<qco> what if you could life in your abstract thoughts?</qco> </h3><br><br>"
  },
  {
    "html": "<h3> <dco>4.24.18&nbsp; \n9:56 pm</dco> &nbsp;<qco> Do you ever have other people listen to your music before you release it to make sure it's good or do you just rely on yourself?</qco> </h3><br><br>"
  },
  {
    "html": "<h3> <dco>4.24.18&nbsp; \n9:26 pm</dco> &nbsp;<qco> Excuse me sir, have you heard the good word of the almighty Shift Key?</qco> </h3><br><br>"
  },
  {
    "html": "<h3> <dco>4.24.18&nbsp; \n8:54 pm</dco> &nbsp;<qco> when did you get the idea of what you do?</qco> </h3><br><br>"
  },
  {
    "html": "<h3> <dco>4.24.18&nbsp; \n8:20 pm</dco> &nbsp;<qco> How did you write some of your older stuff</qco> </h3><br><br>"
  }
]
